Metadata-Version: 2.1
Name: odoo14-addon-stock-quant-package-dimension
Version: 14.0.2.2.0
Summary: Use dimensions on packages
Home-page: https://github.com/OCA/stock-logistics-workflow
Author: Camptocamp, Odoo Community Association (OCA)
Author-email: support@odoo-community.org
License: AGPL-3
Platform: UNKNOWN
Classifier: Programming Language :: Python
Classifier: Framework :: Odoo
Classifier: Framework :: Odoo :: 14.0
Classifier: License :: OSI Approved :: GNU Affero General Public License v3
Classifier: Development Status :: 4 - Beta
Requires-Python: >=3.6
Requires-Dist: odoo14-addon-product-packaging-dimension
Requires-Dist: odoo14-addon-stock-quant-package-product-packaging
Requires-Dist: odoo (<14.1dev,>=14.0a)
